scientistmetrics/__init__.py
scientistmetrics/accuracy_score.py
scientistmetrics/association.py
scientistmetrics/average_precision_score.py
scientistmetrics/balanced_accuracy_score.py
scientistmetrics/brier_score_loss.py
scientistmetrics/check_autocorrelation.py
scientistmetrics/check_heteroscedasticity.py
scientistmetrics/check_kmo.py
scientistmetrics/check_model.py
scientistmetrics/check_normality.py
scientistmetrics/check_overdispersion.py
scientistmetrics/check_spericity_bartlett.py
scientistmetrics/check_symetric.py
scientistmetrics/coefficients.py
scientistmetrics/compare_performance.py
scientistmetrics/diff.py
scientistmetrics/efron_rsquare.py
scientistmetrics/error_rate.py
scientistmetrics/explained_variance_score.py
scientistmetrics/extractAIC.py
scientistmetrics/extractAICC.py
scientistmetrics/extractBIC.py
scientistmetrics/f1_score.py
scientistmetrics/ggroc.py
scientistmetrics/hosmerlemeshowtest.py
scientistmetrics/lag.py
scientistmetrics/likelihoodratiotest.py
scientistmetrics/logLik.py
scientistmetrics/log_loss.py
scientistmetrics/mae.py
scientistmetrics/mannwhitneytest.py
scientistmetrics/mape.py
scientistmetrics/max_error.py
scientistmetrics/mdae.py
scientistmetrics/mdape.py
scientistmetrics/model_performance.py
scientistmetrics/mse.py
scientistmetrics/multiclass_roc.py
scientistmetrics/performance.py
scientistmetrics/powerset.py
scientistmetrics/precision_score.py
scientistmetrics/r2.py
scientistmetrics/r2_count.py
scientistmetrics/r2_count_adj.py
scientistmetrics/r2_coxsnell.py
scientistmetrics/r2_efron.py
scientistmetrics/r2_kullback.py
scientistmetrics/r2_mcfadden.py
scientistmetrics/r2_mckelvey.py
scientistmetrics/r2_nagelkerke.py
scientistmetrics/r2_score.py
scientistmetrics/r2_somers.py
scientistmetrics/r2_tjur.py
scientistmetrics/r2_xu.py
scientistmetrics/recall_score.py
scientistmetrics/residuals.py
scientistmetrics/rmse.py
scientistmetrics/roc_auc_score.py
scientistmetrics/rstandard.py
scientistmetrics/rstudent.py
scientistmetrics-0.0.4.dist-info/LICENSE
scientistmetrics-0.0.4.dist-info/METADATA
scientistmetrics-0.0.4.dist-info/WHEEL
scientistmetrics-0.0.4.dist-info/top_level.txt
scientistmetrics-0.0.4.dist-info/RECORD
