Metadata-Version: 2.1
Name: scientistmetrics
Version: 0.0.4
Summary: Python package for metrics and scoring : quantifying the quality of predictions
Home-page: https://github.com/enfantbenidedieu/scientistmetrics
Author: Duverier DJIFACK ZEBAZE
Author-email: duverierdjifack@gmail.com
Classifier: Programming Language :: Python :: 3
Classifier: License :: OSI Approved :: MIT License
Classifier: Operating System :: OS Independent
Requires-Python: >=3.10
License-File: LICENSE
Requires-Dist: numpy (>=1.26.4)
Requires-Dist: pandas (>=2.2.2)
Requires-Dist: scikit-learn (>=1.2.2)
Requires-Dist: plotnine (>=0.10.1)
Requires-Dist: statsmodels (>=0.14.0)
Requires-Dist: scipy (>=1.10.1)
